{
  "name": "nssp",
  "title": "Nssp",
  "licence": {
    "url": "http://opendatacommons.org/licenses/pddl",
    "name": "Open Data Commons Public Domain",
    "version": "1.0",
    "id": "odc-pddl"
  },
  "resources": [
    {
      "bytes": 2515317,
      "encoding": "ISO-8859-1",
      "md5": "98ec73521735937d712b8339382e95c2",
      "format": "csv",
      "name": "data.csv",
      "filename": "data.csv.gz",
      "versions": {},
      "source": [],
      "ids": [
        {
          "variable": "geography"
        }
      ],
      "id_length": 0,
      "time": "time",
      "profile": "data-resource",
      "created": "2025-07-07 22:41:40",
      "last_modified": "2025-07-11 11:05:01.18206",
      "row_count": 443088,
      "entity_count": 3077,
      "schema": {
        "fields": [
          {
            "name": "geography",
            "duplicates": 440011,
            "time_range": [0, 143],
            "type": "string",
            "missing": 0,
            "table": {
              "0": 144,
              "1000": 144,
              "10000": 144,
              "10001": 144,
              "10003": 144,
              "10005": 144,
              "1001": 144,
              "1003": 144,
              "1005": 144,
              "1007": 144,
              "1009": 144,
              "1011": 144,
              "1013": 144,
              "1015": 144,
              "1017": 144,
              "1019": 144,
              "1021": 144,
              "1023": 144,
              "1025": 144,
              "1027": 144,
              "1029": 144,
              "1031": 144,
              "1033": 144,
              "1035": 144,
              "1037": 144,
              "1039": 144,
              "1041": 144,
              "1043": 144,
              "1045": 144,
              "1047": 144,
              "1049": 144,
              "1051": 144,
              "1053": 144,
              "1055": 144,
              "1057": 144,
              "1059": 144,
              "1061": 144,
              "1063": 144,
              "1065": 144,
              "1067": 144,
              "1069": 144,
              "1071": 144,
              "1073": 144,
              "1075": 144,
              "1077": 144,
              "1079": 144,
              "1081": 144,
              "1083": 144,
              "1085": 144,
              "1087": 144,
              "1089": 144,
              "1091": 144,
              "1093": 144,
              "1095": 144,
              "1097": 144,
              "1099": 144,
              "11000": 144,
              "11001": 144,
              "1101": 144,
              "1103": 144,
              "1105": 144,
              "1107": 144,
              "1109": 144,
              "1111": 144,
              "1113": 144,
              "1115": 144,
              "1117": 144,
              "1119": 144,
              "1121": 144,
              "1123": 144,
              "1125": 144,
              "1127": 144,
              "1129": 144,
              "1131": 144,
              "1133": 144,
              "12000": 144,
              "12001": 144,
              "12003": 144,
              "12005": 144,
              "12007": 144,
              "12009": 144,
              "12011": 144,
              "12013": 144,
              "12015": 144,
              "12017": 144,
              "12019": 144,
              "12021": 144,
              "12023": 144,
              "12027": 144,
              "12029": 144,
              "12031": 144,
              "12033": 144,
              "12035": 144,
              "12037": 144,
              "12039": 144,
              "12041": 144,
              "12043": 144,
              "12045": 144,
              "12047": 144,
              "12049": 144,
              "12051": 144,
              "12053": 144,
              "12055": 144,
              "12057": 144,
              "12059": 144,
              "12061": 144,
              "12063": 144,
              "12065": 144,
              "12067": 144,
              "12069": 144,
              "12071": 144,
              "12073": 144,
              "12075": 144,
              "12077": 144,
              "12079": 144,
              "12081": 144,
              "12083": 144,
              "12085": 144,
              "12086": 144,
              "12087": 144,
              "12089": 144,
              "12091": 144,
              "12093": 144,
              "12095": 144,
              "12097": 144,
              "12099": 144,
              "12101": 144,
              "12103": 144,
              "12105": 144,
              "12107": 144,
              "12109": 144,
              "12111": 144,
              "12113": 144,
              "12115": 144,
              "12117": 144,
              "12119": 144,
              "12121": 144,
              "12123": 144,
              "12125": 144,
              "12127": 144,
              "12129": 144,
              "12131": 144,
              "12133": 144,
              "13000": 144,
              "13001": 144,
              "13003": 144,
              "13005": 144,
              "13007": 144,
              "13009": 144,
              "13011": 144,
              "13013": 144,
              "13015": 144,
              "13017": 144,
              "13019": 144,
              "13021": 144,
              "13023": 144,
              "13025": 144,
              "13027": 144,
              "13029": 144,
              "13031": 144,
              "13033": 144,
              "13035": 144,
              "13037": 144,
              "13039": 144,
              "13043": 144,
              "13045": 144,
              "13047": 144,
              "13049": 144,
              "13051": 144,
              "13053": 144,
              "13055": 144,
              "13057": 144,
              "13059": 144,
              "13061": 144,
              "13063": 144,
              "13065": 144,
              "13067": 144,
              "13069": 144,
              "13071": 144,
              "13073": 144,
              "13075": 144,
              "13077": 144,
              "13079": 144,
              "13081": 144,
              "13083": 144,
              "13085": 144,
              "13087": 144,
              "13089": 144,
              "13091": 144,
              "13093": 144,
              "13095": 144,
              "13097": 144,
              "13099": 144,
              "13101": 144,
              "13103": 144,
              "13105": 144,
              "13107": 144,
              "13109": 144,
              "13111": 144,
              "13113": 144,
              "13115": 144,
              "13117": 144,
              "13119": 144,
              "13121": 144,
              "13123": 144,
              "13125": 144,
              "13127": 144,
              "13129": 144,
              "13131": 144,
              "13133": 144,
              "13135": 144,
              "13137": 144,
              "13139": 144,
              "13141": 144,
              "13143": 144,
              "13145": 144,
              "13147": 144,
              "13149": 144,
              "13151": 144,
              "13153": 144,
              "13155": 144,
              "13157": 144,
              "13159": 144,
              "13161": 144,
              "13163": 144,
              "13165": 144,
              "13167": 144,
              "13169": 144,
              "13171": 144,
              "13173": 144,
              "13175": 144,
              "13177": 144,
              "13179": 144,
              "13181": 144,
              "13183": 144,
              "13185": 144,
              "13187": 144,
              "13189": 144,
              "13191": 144,
              "13193": 144,
              "13195": 144,
              "13197": 144,
              "13199": 144,
              "13201": 144,
              "13205": 144,
              "13207": 144,
              "13209": 144,
              "13211": 144,
              "13213": 144,
              "13215": 144,
              "13217": 144,
              "13219": 144,
              "13221": 144,
              "13223": 144,
              "13225": 144,
              "13227": 144,
              "13229": 144,
              "13231": 144,
              "13233": 144,
              "13235": 144,
              "13237": 144,
              "13239": 144,
              "13241": 144,
              "13243": 144,
              "13245": 144,
              "13247": 144,
              "13249": 144,
              "13251": 144,
              "13253": 144,
              "13255": 144,
              "13257": 144,
              "13259": 144,
              "13261": 144,
              "13263": 144,
              "13265": 144,
              "13267": 144,
              "13269": 144,
              "13271": 144,
              "13273": 144,
              "13275": 144,
              "13277": 144,
              "13279": 144,
              "13281": 144,
              "13283": 144,
              "13285": 144,
              "13287": 144,
              "13289": 144,
              "13291": 144,
              "13293": 144,
              "13295": 144,
              "13297": 144,
              "13299": 144,
              "13301": 144,
              "13303": 144,
              "13305": 144,
              "13307": 144,
              "13309": 144,
              "13311": 144,
              "13313": 144,
              "13315": 144,
              "13317": 144,
              "13319": 144,
              "13321": 144,
              "15000": 144,
              "15001": 144,
              "15003": 144,
              "15005": 144,
              "15007": 144,
              "15009": 144,
              "16000": 144,
              "16001": 144,
              "16003": 144,
              "16005": 144,
              "16007": 144,
              "16009": 144,
              "16011": 144,
              "16013": 144,
              "16015": 144,
              "16017": 144,
              "16019": 144,
              "16021": 144,
              "16023": 144,
              "16025": 144,
              "16027": 144,
              "16029": 144,
              "16031": 144,
              "16033": 144,
              "16035": 144,
              "16037": 144,
              "16039": 144,
              "16041": 144,
              "16043": 144,
              "16045": 144,
              "16047": 144,
              "16049": 144,
              "16051": 144,
              "16053": 144,
              "16055": 144,
              "16057": 144,
              "16059": 144,
              "16061": 144,
              "16063": 144,
              "16065": 144,
              "16067": 144,
              "16069": 144,
              "16071": 144,
              "16073": 144,
              "16075": 144,
              "16077": 144,
              "16079": 144,
              "16081": 144,
              "16083": 144,
              "16085": 144,
              "16087": 144,
              "17000": 144,
              "17001": 144,
              "17003": 144,
              "17005": 144,
              "17007": 144,
              "17009": 144,
              "17011": 144,
              "17013": 144,
              "17015": 144,
              "17017": 144,
              "17019": 144,
              "17021": 144,
              "17023": 144,
              "17025": 144,
              "17027": 144,
              "17029": 144,
              "17031": 144,
              "17033": 144,
              "17035": 144,
              "17037": 144,
              "17039": 144,
              "17041": 144,
              "17043": 144,
              "17045": 144,
              "17047": 144,
              "17049": 144,
              "17051": 144,
              "17053": 144,
              "17055": 144,
              "17057": 144,
              "17059": 144,
              "17061": 144,
              "17063": 144,
              "17065": 144,
              "17067": 144,
              "17069": 144,
              "17071": 144,
              "17073": 144,
              "17075": 144,
              "17077": 144,
              "17079": 144,
              "17081": 144,
              "17083": 144,
              "17085": 144,
              "17087": 144,
              "17089": 144,
              "17091": 144,
              "17093": 144,
              "17095": 144,
              "17097": 144,
              "17099": 144,
              "17101": 144,
              "17103": 144,
              "17105": 144,
              "17107": 144,
              "17109": 144,
              "17111": 144,
              "17113": 144,
              "17115": 144,
              "17117": 144,
              "17119": 144,
              "17121": 144,
              "17123": 144,
              "17125": 144,
              "17127": 144,
              "17129": 144,
              "17131": 144,
              "17133": 144,
              "17135": 144,
              "17137": 144,
              "17139": 144,
              "17141": 144,
              "17143": 144,
              "17145": 144,
              "17147": 144,
              "17149": 144,
              "17151": 144,
              "17153": 144,
              "17155": 144,
              "17157": 144,
              "17159": 144,
              "17161": 144,
              "17163": 144,
              "17165": 144,
              "17167": 144,
              "17169": 144,
              "17171": 144,
              "17173": 144,
              "17175": 144,
              "17177": 144,
              "17179": 144,
              "17181": 144,
              "17183": 144,
              "17185": 144,
              "17187": 144,
              "17189": 144,
              "17191": 144,
              "17193": 144,
              "17195": 144,
              "17197": 144,
              "17199": 144,
              "17201": 144,
              "17203": 144,
              "18000": 144,
              "18001": 144,
              "18003": 144,
              "18005": 144,
              "18007": 144,
              "18009": 144,
              "18011": 144,
              "18013": 144,
              "18015": 144,
              "18017": 144,
              "18019": 144,
              "18021": 144,
              "18023": 144,
              "18025": 144,
              "18027": 144,
              "18029": 144,
              "18031": 144,
              "18033": 144,
              "18035": 144,
              "18037": 144,
              "18039": 144,
              "18041": 144,
              "18043": 144,
              "18045": 144,
              "18047": 144,
              "18049": 144,
              "18051": 144,
              "18053": 144,
              "18055": 144,
              "18057": 144,
              "18059": 144,
              "18061": 144,
              "18063": 144,
              "18065": 144,
              "18067": 144,
              "18069": 144,
              "18071": 144,
              "18073": 144,
              "18075": 144,
              "18077": 144,
              "18079": 144,
              "18081": 144,
              "18083": 144,
              "18085": 144,
              "18087": 144,
              "18089": 144,
              "18091": 144,
              "18093": 144,
              "18095": 144,
              "18097": 144,
              "18099": 144,
              "18101": 144,
              "18103": 144,
              "18105": 144,
              "18107": 144,
              "18109": 144,
              "18111": 144,
              "18113": 144,
              "18115": 144,
              "18117": 144,
              "18119": 144,
              "18121": 144,
              "18123": 144,
              "18125": 144,
              "18127": 144,
              "18129": 144,
              "18131": 144,
              "18133": 144,
              "18135": 144,
              "18137": 144,
              "18139": 144,
              "18141": 144,
              "18143": 144,
              "18145": 144,
              "18147": 144,
              "18149": 144,
              "18151": 144,
              "18153": 144,
              "18155": 144,
              "18157": 144,
              "18159": 144,
              "18161": 144,
              "18163": 144,
              "18165": 144,
              "18167": 144,
              "18169": 144,
              "18171": 144,
              "18173": 144,
              "18175": 144,
              "18177": 144,
              "18179": 144,
              "18181": 144,
              "18183": 144,
              "19000": 144,
              "19001": 144,
              "19003": 144,
              "19005": 144,
              "19007": 144,
              "19009": 144,
              "19011": 144,
              "19013": 144,
              "19015": 144,
              "19017": 144,
              "19019": 144,
              "19021": 144,
              "19023": 144,
              "19025": 144,
              "19027": 144,
              "19029": 144,
              "19031": 144,
              "19033": 144,
              "19035": 144,
              "19037": 144,
              "19039": 144,
              "19041": 144,
              "19043": 144,
              "19045": 144,
              "19047": 144,
              "19049": 144,
              "19051": 144,
              "19053": 144,
              "19055": 144,
              "19057": 144,
              "19059": 144,
              "19061": 144,
              "19063": 144,
              "19065": 144,
              "19067": 144,
              "19069": 144,
              "19071": 144,
              "19073": 144,
              "19075": 144,
              "19077": 144,
              "19079": 144,
              "19081": 144,
              "19083": 144,
              "19085": 144,
              "19087": 144,
              "19089": 144,
              "19091": 144,
              "19093": 144,
              "19095": 144,
              "19097": 144,
              "19099": 144,
              "19101": 144,
              "19103": 144,
              "19105": 144,
              "19107": 144,
              "19109": 144,
              "19111": 144,
              "19113": 144,
              "19115": 144,
              "19117": 144,
              "19119": 144,
              "19121": 144,
              "19123": 144,
              "19125": 144,
              "19127": 144,
              "19129": 144,
              "19131": 144,
              "19133": 144,
              "19135": 144,
              "19137": 144,
              "19139": 144,
              "19141": 144,
              "19143": 144,
              "19145": 144,
              "19147": 144,
              "19149": 144,
              "19151": 144,
              "19153": 144,
              "19155": 144,
              "19157": 144,
              "19159": 144,
              "19161": 144,
              "19163": 144,
              "19165": 144,
              "19167": 144,
              "19169": 144,
              "19171": 144,
              "19173": 144,
              "19175": 144,
              "19177": 144,
              "19179": 144,
              "19181": 144,
              "19183": 144,
              "19185": 144,
              "19187": 144,
              "19189": 144,
              "19191": 144,
              "19193": 144,
              "19195": 144,
              "19197": 144,
              "2000": 144,
              "20000": 144,
              "20001": 144,
              "20003": 144,
              "20005": 144,
              "20007": 144,
              "20009": 144,
              "20011": 144,
              "20013": 144,
              "20015": 144,
              "20017": 144,
              "20019": 144,
              "20021": 144,
              "20023": 144,
              "20025": 144,
              "20027": 144,
              "20029": 144,
              "20031": 144,
              "20033": 144,
              "20035": 144,
              "20037": 144,
              "20039": 144,
              "20041": 144,
              "20043": 144,
              "20045": 144,
              "20047": 144,
              "20049": 144,
              "20051": 144,
              "20053": 144,
              "20055": 144,
              "20057": 144,
              "20059": 144,
              "20061": 144,
              "20063": 144,
              "20065": 144,
              "20067": 144,
              "20069": 144,
              "20071": 144,
              "20073": 144,
              "20075": 144,
              "20077": 144,
              "20079": 144,
              "20081": 144,
              "20083": 144,
              "20085": 144,
              "20087": 144,
              "20089": 144,
              "20091": 144,
              "20093": 144,
              "20095": 144,
              "20097": 144,
              "20099": 144,
              "20101": 144,
              "20103": 144,
              "20105": 144,
              "20107": 144,
              "20109": 144,
              "20111": 144,
              "20113": 144,
              "20115": 144,
              "20117": 144,
              "20119": 144,
              "20121": 144,
              "20123": 144,
              "20125": 144,
              "20127": 144,
              "20129": 144,
              "2013": 144,
              "20131": 144,
              "20133": 144,
              "20135": 144,
              "20137": 144,
              "20139": 144,
              "20141": 144,
              "20143": 144,
              "20145": 144,
              "20147": 144,
              "20149": 144,
              "20151": 144,
              "20153": 144,
              "20155": 144,
              "20157": 144,
              "20159": 144,
              "2016": 144,
              "20161": 144,
              "20163": 144,
              "20165": 144,
              "20167": 144,
              "20169": 144,
              "20171": 144,
              "20173": 144,
              "20175": 144,
              "20177": 144,
              "20179": 144,
              "20181": 144,
              "20183": 144,
              "20185": 144,
              "20187": 144,
              "20189": 144,
              "20191": 144,
              "20193": 144,
              "20195": 144,
              "20197": 144,
              "20199": 144,
              "2020": 144,
              "20201": 144,
              "20203": 144,
              "20205": 144,
              "20207": 144,
              "20209": 144,
              "2050": 144,
              "2060": 144,
              "2068": 144,
              "2070": 144,
              "2090": 144,
              "2100": 144,
              "21000": 144,
              "21001": 144,
              "21003": 144,
              "21005": 144,
              "21007": 144,
              "21009": 144,
              "21011": 144,
              "21013": 144,
              "21015": 144,
              "21017": 144,
              "21019": 144,
              "21021": 144,
              "21023": 144,
              "21025": 144,
              "21027": 144,
              "21029": 144,
              "21031": 144,
              "21033": 144,
              "21035": 144,
              "21037": 144,
              "21039": 144,
              "21041": 144,
              "21043": 144,
              "21045": 144,
              "21047": 144,
              "21049": 144,
              "21051": 144,
              "21053": 144,
              "21055": 144,
              "21057": 144,
              "21059": 144,
              "21061": 144,
              "21063": 144,
              "21065": 144,
              "21067": 144,
              "21069": 144,
              "21071": 144,
              "21073": 144,
              "21075": 144,
              "21077": 144,
              "21079": 144,
              "21081": 144,
              "21083": 144,
              "21085": 144,
              "21087": 144,
              "21089": 144,
              "21091": 144,
              "21093": 144,
              "21095": 144,
              "21097": 144,
              "21099": 144,
              "2110": 144,
              "21101": 144,
              "21103": 144,
              "21105": 144,
              "21107": 144,
              "21109": 144,
              "21111": 144,
              "21113": 144,
              "21115": 144,
              "21117": 144,
              "21119": 144,
              "21121": 144,
              "21123": 144,
              "21125": 144,
              "21127": 144,
              "21129": 144,
              "21131": 144,
              "21133": 144,
              "21135": 144,
              "21137": 144,
              "21139": 144,
              "21141": 144,
              "21143": 144,
              "21145": 144,
              "21147": 144,
              "21149": 144,
              "21151": 144,
              "21153": 144,
              "21155": 144,
              "21157": 144,
              "21159": 144,
              "21161": 144,
              "21163": 144,
              "21165": 144,
              "21167": 144,
              "21169": 144,
              "21171": 144,
              "21173": 144,
              "21175": 144,
              "21177": 144,
              "21179": 144,
              "21181": 144,
              "21183": 144,
              "21185": 144,
              "21187": 144,
              "21189": 144,
              "21191": 144,
              "21193": 144,
              "21195": 144,
              "21197": 144,
              "21199": 144,
              "21201": 144,
              "21203": 144,
              "21205": 144,
              "21207": 144,
              "21209": 144,
              "21211": 144,
              "21213": 144,
              "21215": 144,
              "21217": 144,
              "21219": 144,
              "2122": 144,
              "21221": 144,
              "21223": 144,
              "21225": 144,
              "21227": 144,
              "21229": 144,
              "21231": 144,
              "21233": 144,
              "21235": 144,
              "21237": 144,
              "21239": 144,
              "2130": 144,
              "2150": 144,
              "2164": 144,
              "2170": 144,
              "2180": 144,
              "2185": 144,
              "2188": 144,
              "22000": 144,
              "22001": 144,
              "22003": 144,
              "22005": 144,
              "22007": 144,
              "22009": 144,
              "2201": 144,
              "22011": 144,
              "22013": 144,
              "22015": 144,
              "22017": 144,
              "22019": 144,
              "22021": 144,
              "22023": 144,
              "22025": 144,
              "22027": 144,
              "22029": 144,
              "22031": 144,
              "22033": 144,
              "22035": 144,
              "22037": 144,
              "22039": 144,
              "22041": 144,
              "22043": 144,
              "22045": 144,
              "22047": 144,
              "22049": 144,
              "22051": 144,
              "22053": 144,
              "22055": 144,
              "22057": 144,
              "22059": 144,
              "22061": 144,
              "22063": 144,
              "22065": 144,
              "22067": 144,
              "22069": 144,
              "22071": 144,
              "22073": 144,
              "22075": 144,
              "22077": 144,
              "22079": 144,
              "22081": 144,
              "22083": 144,
              "22085": 144,
              "22087": 144,
              "22089": 144,
              "22091": 144,
              "22093": 144,
              "22095": 144,
              "22097": 144,
              "22099": 144,
              "22101": 144,
              "22103": 144,
              "22105": 144,
              "22107": 144,
              "22109": 144,
              "22111": 144,
              "22113": 144,
              "22115": 144,
              "22117": 144,
              "22119": 144,
              "22121": 144,
              "22123": 144,
              "22125": 144,
              "22127": 144,
              "2220": 144,
              "2232": 144,
              "2240": 144,
              "2261": 144,
              "2270": 144,
              "2280": 144,
              "2282": 144,
              "2290": 144,
              "23000": 144,
              "23001": 144,
              "23003": 144,
              "23005": 144,
              "23007": 144,
              "23009": 144,
              "23011": 144,
              "23013": 144,
              "23015": 144,
              "23017": 144,
              "23019": 144,
              "23021": 144,
              "23023": 144,
              "23025": 144,
              "23027": 144,
              "23029": 144,
              "23031": 144,
              "24000": 144,
              "24001": 144,
              "24003": 144,
              "24005": 144,
              "24009": 144,
              "24011": 144,
              "24013": 144,
              "24015": 144,
              "24017": 144,
              "24019": 144,
              "24021": 144,
              "24023": 144,
              "24025": 144,
              "24027": 144,
              "24029": 144,
              "24031": 144,
              "24033": 144,
              "24035": 144,
              "24037": 144,
              "24039": 144,
              "24041": 144,
              "24043": 144,
              "24045": 144,
              "24047": 144,
              "24510": 144,
              "25000": 144,
              "25001": 144,
              "25003": 144,
              "25005": 144,
              "25007": 144,
              "25009": 144,
              "25011": 144,
              "25013": 144,
              "25015": 144,
              "25017": 144,
              "25019": 144,
              "25021": 144,
              "25023": 144,
              "25025": 144,
              "25027": 144,
              "26000": 144,
              "26001": 144,
              "26003": 144,
              "26005": 144,
              "26007": 144,
              "26009": 144,
              "26011": 144,
              "26013": 144,
              "26015": 144,
              "26017": 144,
              "26019": 144,
              "26021": 144,
              "26023": 144,
              "26025": 144,
              "26027": 144,
              "26029": 144,
              "26031": 144,
              "26033": 144,
              "26035": 144,
              "26037": 144,
              "26039": 144,
              "26041": 144,
              "26043": 144,
              "26045": 144,
              "26047": 144,
              "26049": 144,
              "26051": 144,
              "26053": 144,
              "26055": 144,
              "26057": 144,
              "26059": 144,
              "26061": 144,
              "26063": 144,
              "26065": 144,
              "26067": 144,
              "26069": 144,
              "26071": 144,
              "26073": 144,
              "26075": 144,
              "26077": 144,
              "26079": 144,
              "26081": 144,
              "26083": 144,
              "26085": 144,
              "26087": 144,
              "26089": 144,
              "26091": 144,
              "26093": 144,
              "26095": 144,
              "26097": 144,
              "26099": 144,
              "26101": 144,
              "26103": 144,
              "26105": 144,
              "26107": 144,
              "26109": 144,
              "26111": 144,
              "26113": 144,
              "26115": 144,
              "26117": 144,
              "26119": 144,
              "26121": 144,
              "26123": 144,
              "26125": 144,
              "26127": 144,
              "26129": 144,
              "26131": 144,
              "26133": 144,
              "26135": 144,
              "26137": 144,
              "26139": 144,
              "26141": 144,
              "26143": 144,
              "26145": 144,
              "26147": 144,
              "26149": 144,
              "26151": 144,
              "26153": 144,
              "26155": 144,
              "26157": 144,
              "26159": 144,
              "26161": 144,
              "26163": 144,
              "26165": 144,
              "27000": 144,
              "27001": 144,
              "27003": 144,
              "27005": 144,
              "27007": 144,
              "27009": 144,
              "27011": 144,
              "27013": 144,
              "27015": 144,
              "27017": 144,
              "27019": 144,
              "27021": 144,
              "27023": 144,
              "27025": 144,
              "27027": 144,
              "27029": 144,
              "27031": 144,
              "27033": 144,
              "27035": 144,
              "27037": 144,
              "27039": 144,
              "27041": 144,
              "27043": 144,
              "27045": 144,
              "27047": 144,
              "27049": 144,
              "27051": 144,
              "27053": 144,
              "27055": 144,
              "27057": 144,
              "27059": 144,
              "27061": 144,
              "27063": 144,
              "27065": 144,
              "27067": 144,
              "27069": 144,
              "27071": 144,
              "27073": 144,
              "27075": 144,
              "27077": 144,
              "27079": 144,
              "27081": 144,
              "27083": 144,
              "27085": 144,
              "27087": 144,
              "27089": 144,
              "27091": 144,
              "27093": 144,
              "27095": 144,
              "27097": 144,
              "27099": 144,
              "27101": 144,
              "27103": 144,
              "27105": 144,
              "27107": 144,
              "27109": 144,
              "27111": 144,
              "27113": 144,
              "27115": 144,
              "27117": 144,
              "27119": 144,
              "27121": 144,
              "27123": 144,
              "27125": 144,
              "27127": 144,
              "27129": 144,
              "27131": 144,
              "27133": 144,
              "27135": 144,
              "27137": 144,
              "27139": 144,
              "27141": 144,
              "27143": 144,
              "27145": 144,
              "27147": 144,
              "27149": 144,
              "27151": 144,
              "27153": 144,
              "27155": 144,
              "27157": 144,
              "27159": 144,
              "27161": 144,
              "27163": 144,
              "27165": 144,
              "27167": 144,
              "27169": 144,
              "27171": 144,
              "27173": 144,
              "28000": 144,
              "28001": 144,
              "28003": 144,
              "28005": 144,
              "28007": 144,
              "28009": 144,
              "28011": 144,
              "28013": 144,
              "28015": 144,
              "28017": 144,
              "28019": 144,
              "28021": 144,
              "28023": 144,
              "28025": 144,
              "28027": 144,
              "28029": 144,
              "28031": 144,
              "28033": 144,
              "28035": 144,
              "28037": 144,
              "28039": 144,
              "28041": 144,
              "28043": 144,
              "28045": 144,
              "28047": 144,
              "28049": 144,
              "28051": 144,
              "28053": 144,
              "28055": 144,
              "28057": 144,
              "28059": 144,
              "28061": 144,
              "28063": 144,
              "28065": 144,
              "28067": 144,
              "28069": 144,
              "28071": 144,
              "28073": 144,
              "28075": 144,
              "28077": 144,
              "28079": 144,
              "28081": 144,
              "28083": 144,
              "28085": 144,
              "28087": 144,
              "28089": 144,
              "28091": 144,
              "28093": 144,
              "28095": 144,
              "28097": 144,
              "28099": 144,
              "28101": 144,
              "28103": 144,
              "28105": 144,
              "28107": 144,
              "28109": 144,
              "28111": 144,
              "28113": 144,
              "28115": 144,
              "28117": 144,
              "28119": 144,
              "28121": 144,
              "28123": 144,
              "28125": 144,
              "28127": 144,
              "28129": 144,
              "28131": 144,
              "28133": 144,
              "28135": 144,
              "28137": 144,
              "28139": 144,
              "28141": 144,
              "28143": 144,
              "28145": 144,
              "28147": 144,
              "28149": 144,
              "28151": 144,
              "28153": 144,
              "28155": 144,
              "28157": 144,
              "28159": 144,
              "28161": 144,
              "28163": 144,
              "30000": 144,
              "30001": 144,
              "30003": 144,
              "30005": 144,
              "30007": 144,
              "30009": 144,
              "30011": 144,
              "30013": 144,
              "30015": 144,
              "30017": 144,
              "30019": 144,
              "30021": 144,
              "30023": 144,
              "30025": 144,
              "30027": 144,
              "30029": 144,
              "30031": 144,
              "30033": 144,
              "30035": 144,
              "30037": 144,
              "30039": 144,
              "30041": 144,
              "30043": 144,
              "30045": 144,
              "30047": 144,
              "30049": 144,
              "30051": 144,
              "30053": 144,
              "30055": 144,
              "30057": 144,
              "30059": 144,
              "30061": 144,
              "30063": 144,
              "30065": 144,
              "30067": 144,
              "30069": 144,
              "30071": 144,
              "30073": 144,
              "30075": 144,
              "30077": 144,
              "30079": 144,
              "30081": 144,
              "30083": 144,
              "30085": 144,
              "30087": 144,
              "30089": 144,
              "30091": 144,
              "30093": 144,
              "30095": 144,
              "30097": 144,
              "30099": 144,
              "30101": 144,
              "30103": 144,
              "30105": 144,
              "30107": 144,
              "30109": 144,
              "30111": 144,
              "31000": 144,
              "31001": 144,
              "31003": 144,
              "31005": 144,
              "31007": 144,
              "31009": 144,
              "31011": 144,
              "31013": 144,
              "31015": 144,
              "31017": 144,
              "31019": 144,
              "31021": 144,
              "31023": 144,
              "31025": 144,
              "31027": 144,
              "31029": 144,
              "31031": 144,
              "31033": 144,
              "31035": 144,
              "31037": 144,
              "31039": 144,
              "31041": 144,
              "31043": 144,
              "31045": 144,
              "31047": 144,
              "31049": 144,
              "31051": 144,
              "31053": 144,
              "31055": 144,
              "31057": 144,
              "31059": 144,
              "31061": 144,
              "31063": 144,
              "31065": 144,
              "31067": 144,
              "31069": 144,
              "31071": 144,
              "31073": 144,
              "31075": 144,
              "31077": 144,
              "31079": 144,
              "31081": 144,
              "31083": 144,
              "31085": 144,
              "31087": 144,
              "31089": 144,
              "31091": 144,
              "31093": 144,
              "31095": 144,
              "31097": 144,
              "31099": 144,
              "31101": 144,
              "31103": 144,
              "31105": 144,
              "31107": 144,
              "31109": 144,
              "31111": 144,
              "31113": 144,
              "31115": 144,
              "31117": 144,
              "31119": 144,
              "31121": 144,
              "31123": 144,
              "31125": 144,
              "31127": 144,
              "31129": 144,
              "31131": 144,
              "31133": 144,
              "31135": 144,
              "31137": 144,
              "31139": 144,
              "31141": 144,
              "31143": 144,
              "31145": 144,
              "31147": 144,
              "31149": 144,
              "31151": 144,
              "31153": 144,
              "31155": 144,
              "31157": 144,
              "31159": 144,
              "31161": 144,
              "31163": 144,
              "31165": 144,
              "31167": 144,
              "31169": 144,
              "31171": 144,
              "31173": 144,
              "31175": 144,
              "31177": 144,
              "31179": 144,
              "31181": 144,
              "31183": 144,
              "31185": 144,
              "32000": 144,
              "32001": 144,
              "32003": 144,
              "32005": 144,
              "32007": 144,
              "32009": 144,
              "32011": 144,
              "32013": 144,
              "32015": 144,
              "32017": 144,
              "32019": 144,
              "32021": 144,
              "32023": 144,
              "32027": 144,
              "32029": 144,
              "32031": 144,
              "32033": 144,
              "32510": 144,
              "33000": 144,
              "33001": 144,
              "33003": 144,
              "33005": 144,
              "33007": 144,
              "33009": 144,
              "33011": 144,
              "33013": 144,
              "33015": 144,
              "33017": 144,
              "33019": 144,
              "34000": 144,
              "34001": 144,
              "34003": 144,
              "34005": 144,
              "34007": 144,
              "34009": 144,
              "34011": 144,
              "34013": 144,
              "34015": 144,
              "34017": 144,
              "34019": 144,
              "34021": 144,
              "34023": 144,
              "34025": 144,
              "34027": 144,
              "34029": 144,
              "34031": 144,
              "34033": 144,
              "34035": 144,
              "34037": 144,
              "34039": 144,
              "34041": 144,
              "35000": 144,
              "35001": 144,
              "35003": 144,
              "35005": 144,
              "35006": 144,
              "35007": 144,
              "35009": 144,
              "35011": 144,
              "35013": 144,
              "35015": 144,
              "35017": 144,
              "35019": 144,
              "35021": 144,
              "35023": 144,
              "35025": 144,
              "35027": 144,
              "35028": 144,
              "35029": 144,
              "35031": 144,
              "35033": 144,
              "35035": 144,
              "35037": 144,
              "35039": 144,
              "35041": 144,
              "35043": 144,
              "35045": 144,
              "35047": 144,
              "35049": 144,
              "35051": 144,
              "35053": 144,
              "35055": 144,
              "35057": 144,
              "35059": 144,
              "35061": 144,
              "36000": 144,
              "36001": 144,
              "36003": 144,
              "36005": 144,
              "36007": 144,
              "36009": 144,
              "36011": 144,
              "36013": 144,
              "36015": 144,
              "36017": 144,
              "36019": 144,
              "36021": 144,
              "36023": 144,
              "36025": 144,
              "36027": 144,
              "36029": 144,
              "36031": 144,
              "36033": 144,
              "36035": 144,
              "36037": 144,
              "36039": 144,
              "36041": 144,
              "36043": 144,
              "36045": 144,
              "36047": 144,
              "36049": 144,
              "36051": 144,
              "36053": 144,
              "36055": 144,
              "36057": 144,
              "36059": 144,
              "36061": 144,
              "36063": 144,
              "36065": 144,
              "36067": 144,
              "36069": 144,
              "36071": 144,
              "36073": 144,
              "36075": 144,
              "36077": 144,
              "36079": 144,
              "36081": 144,
              "36083": 144,
              "36085": 144,
              "36087": 144,
              "36089": 144,
              "36091": 144,
              "36093": 144,
              "36095": 144,
              "36097": 144,
              "36099": 144,
              "36101": 144,
              "36103": 144,
              "36105": 144,
              "36107": 144,
              "36109": 144,
              "36111": 144,
              "36113": 144,
              "36115": 144,
              "36117": 144,
              "36119": 144,
              "36121": 144,
              "36123": 144,
              "37000": 144,
              "37001": 144,
              "37003": 144,
              "37005": 144,
              "37007": 144,
              "37009": 144,
              "37011": 144,
              "37013": 144,
              "37015": 144,
              "37017": 144,
              "37019": 144,
              "37021": 144,
              "37023": 144,
              "37025": 144,
              "37027": 144,
              "37029": 144,
              "37031": 144,
              "37033": 144,
              "37035": 144,
              "37037": 144,
              "37039": 144,
              "37041": 144,
              "37043": 144,
              "37045": 144,
              "37047": 144,
              "37049": 144,
              "37051": 144,
              "37053": 144,
              "37055": 144,
              "37057": 144,
              "37059": 144,
              "37061": 144,
              "37063": 144,
              "37065": 144,
              "37067": 144,
              "37069": 144,
              "37071": 144,
              "37073": 144,
              "37075": 144,
              "37077": 144,
              "37079": 144,
              "37081": 144,
              "37083": 144,
              "37085": 144,
              "37087": 144,
              "37089": 144,
              "37091": 144,
              "37093": 144,
              "37095": 144,
              "37097": 144,
              "37099": 144,
              "37101": 144,
              "37103": 144,
              "37105": 144,
              "37107": 144,
              "37109": 144,
              "37111": 144,
              "37113": 144,
              "37115": 144,
              "37117": 144,
              "37119": 144,
              "37121": 144,
              "37123": 144,
              "37125": 144,
              "37127": 144,
              "37129": 144,
              "37131": 144,
              "37133": 144,
              "37135": 144,
              "37137": 144,
              "37139": 144,
              "37141": 144,
              "37143": 144,
              "37145": 144,
              "37147": 144,
              "37149": 144,
              "37151": 144,
              "37153": 144,
              "37155": 144,
              "37157": 144,
              "37159": 144,
              "37161": 144,
              "37163": 144,
              "37165": 144,
              "37167": 144,
              "37169": 144,
              "37171": 144,
              "37173": 144,
              "37175": 144,
              "37177": 144,
              "37179": 144,
              "37181": 144,
              "37183": 144,
              "37185": 144,
              "37187": 144,
              "37189": 144,
              "37191": 144,
              "37193": 144,
              "37195": 144,
              "37197": 144,
              "37199": 144,
              "38000": 144,
              "38001": 144,
              "38003": 144,
              "38005": 144,
              "38007": 144,
              "38009": 144,
              "38011": 144,
              "38013": 144,
              "38015": 144,
              "38017": 144,
              "38019": 144,
              "38021": 144,
              "38023": 144,
              "38025": 144,
              "38027": 144,
              "38029": 144,
              "38031": 144,
              "38033": 144,
              "38035": 144,
              "38037": 144,
              "38039": 144,
              "38041": 144,
              "38043": 144,
              "38045": 144,
              "38047": 144,
              "38049": 144,
              "38051": 144,
              "38053": 144,
              "38055": 144,
              "38057": 144,
              "38059": 144,
              "38061": 144,
              "38063": 144,
              "38065": 144,
              "38067": 144,
              "38069": 144,
              "38071": 144,
              "38073": 144,
              "38075": 144,
              "38077": 144,
              "38079": 144,
              "38081": 144,
              "38083": 144,
              "38085": 144,
              "38087": 144,
              "38089": 144,
              "38091": 144,
              "38093": 144,
              "38095": 144,
              "38097": 144,
              "38099": 144,
              "38101": 144,
              "38103": 144,
              "38105": 144,
              "39000": 144,
              "39001": 144,
              "39003": 144,
              "39005": 144,
              "39007": 144,
              "39009": 144,
              "39011": 144,
              "39013": 144,
              "39015": 144,
              "39017": 144,
              "39019": 144,
              "39021": 144,
              "39023": 144,
              "39025": 144,
              "39027": 144,
              "39029": 144,
              "39031": 144,
              "39033": 144,
              "39035": 144,
              "39037": 144,
              "39039": 144,
              "39041": 144,
              "39043": 144,
              "39045": 144,
              "39047": 144,
              "39049": 144,
              "39051": 144,
              "39053": 144,
              "39055": 144,
              "39057": 144,
              "39059": 144,
              "39061": 144,
              "39063": 144,
              "39065": 144,
              "39067": 144,
              "39069": 144,
              "39071": 144,
              "39073": 144,
              "39075": 144,
              "39077": 144,
              "39079": 144,
              "39081": 144,
              "39083": 144,
              "39085": 144,
              "39087": 144,
              "39089": 144,
              "39091": 144,
              "39093": 144,
              "39095": 144,
              "39097": 144,
              "39099": 144,
              "39101": 144,
              "39103": 144,
              "39105": 144,
              "39107": 144,
              "39109": 144,
              "39111": 144,
              "39113": 144,
              "39115": 144,
              "39117": 144,
              "39119": 144,
              "39121": 144,
              "39123": 144,
              "39125": 144,
              "39127": 144,
              "39129": 144,
              "39131": 144,
              "39133": 144,
              "39135": 144,
              "39137": 144,
              "39139": 144,
              "39141": 144,
              "39143": 144,
              "39145": 144,
              "39147": 144,
              "39149": 144,
              "39151": 144,
              "39153": 144,
              "39155": 144,
              "39157": 144,
              "39159": 144,
              "39161": 144,
              "39163": 144,
              "39165": 144,
              "39167": 144,
              "39169": 144,
              "39171": 144,
              "39173": 144,
              "39175": 144,
              "4000": 144,
              "40000": 144,
              "40001": 144,
              "40003": 144,
              "40005": 144,
              "40007": 144,
              "40009": 144,
              "4001": 144,
              "40011": 144,
              "40013": 144,
              "40015": 144,
              "40017": 144,
              "40019": 144,
              "40021": 144,
              "40023": 144,
              "40025": 144,
              "40027": 144,
              "40029": 144,
              "4003": 144,
              "40031": 144,
              "40033": 144,
              "40035": 144,
              "40037": 144,
              "40039": 144,
              "40041": 144,
              "40043": 144,
              "40045": 144,
              "40047": 144,
              "40049": 144,
              "4005": 144,
              "40051": 144,
              "40053": 144,
              "40055": 144,
              "40057": 144,
              "40059": 144,
              "40061": 144,
              "40063": 144,
              "40065": 144,
              "40067": 144,
              "40069": 144,
              "4007": 144,
              "40071": 144,
              "40073": 144,
              "40075": 144,
              "40077": 144,
              "40079": 144,
              "40081": 144,
              "40083": 144,
              "40085": 144,
              "40087": 144,
              "40089": 144,
              "4009": 144,
              "40091": 144,
              "40093": 144,
              "40095": 144,
              "40097": 144,
              "40099": 144,
              "40101": 144,
              "40103": 144,
              "40105": 144,
              "40107": 144,
              "40109": 144,
              "4011": 144,
              "40111": 144,
              "40113": 144,
              "40115": 144,
              "40117": 144,
              "40119": 144,
              "4012": 144,
              "40121": 144,
              "40123": 144,
              "40125": 144,
              "40127": 144,
              "40129": 144,
              "4013": 144,
              "40131": 144,
              "40133": 144,
              "40135": 144,
              "40137": 144,
              "40139": 144,
              "40141": 144,
              "40143": 144,
              "40145": 144,
              "40147": 144,
              "40149": 144,
              "4015": 144,
              "40151": 144,
              "40153": 144,
              "4017": 144,
              "4019": 144,
              "4021": 144,
              "4023": 144,
              "4025": 144,
              "4027": 144,
              "41000": 144,
              "41001": 144,
              "41003": 144,
              "41005": 144,
              "41007": 144,
              "41009": 144,
              "41011": 144,
              "41013": 144,
              "41015": 144,
              "41017": 144,
              "41019": 144,
              "41021": 144,
              "41023": 144,
              "41025": 144,
              "41027": 144,
              "41029": 144,
              "41031": 144,
              "41033": 144,
              "41035": 144,
              "41037": 144,
              "41039": 144,
              "41041": 144,
              "41043": 144,
              "41045": 144,
              "41047": 144,
              "41049": 144,
              "41051": 144,
              "41053": 144,
              "41055": 144,
              "41057": 144,
              "41059": 144,
              "41061": 144,
              "41063": 144,
              "41065": 144,
              "41067": 144,
              "41069": 144,
              "41071": 144,
              "42000": 144,
              "42001": 144,
              "42003": 144,
              "42005": 144,
              "42007": 144,
              "42009": 144,
              "42011": 144,
              "42013": 144,
              "42015": 144,
              "42017": 144,
              "42019": 144,
              "42021": 144,
              "42023": 144,
              "42025": 144,
              "42027": 144,
              "42029": 144,
              "42031": 144,
              "42033": 144,
              "42035": 144,
              "42037": 144,
              "42039": 144,
              "42041": 144,
              "42043": 144,
              "42045": 144,
              "42047": 144,
              "42049": 144,
              "42051": 144,
              "42053": 144,
              "42055": 144,
              "42057": 144,
              "42059": 144,
              "42061": 144,
              "42063": 144,
              "42065": 144,
              "42067": 144,
              "42069": 144,
              "42071": 144,
              "42073": 144,
              "42075": 144,
              "42077": 144,
              "42079": 144,
              "42081": 144,
              "42083": 144,
              "42085": 144,
              "42087": 144,
              "42089": 144,
              "42091": 144,
              "42093": 144,
              "42095": 144,
              "42097": 144,
              "42099": 144,
              "42101": 144,
              "42103": 144,
              "42105": 144,
              "42107": 144,
              "42109": 144,
              "42111": 144,
              "42113": 144,
              "42115": 144,
              "42117": 144,
              "42119": 144,
              "42121": 144,
              "42123": 144,
              "42125": 144,
              "42127": 144,
              "42129": 144,
              "42131": 144,
              "42133": 144,
              "44000": 144,
              "44001": 144,
              "44003": 144,
              "44005": 144,
              "44007": 144,
              "44009": 144,
              "45000": 144,
              "45001": 144,
              "45003": 144,
              "45005": 144,
              "45007": 144,
              "45009": 144,
              "45011": 144,
              "45013": 144,
              "45015": 144,
              "45017": 144,
              "45019": 144,
              "45021": 144,
              "45023": 144,
              "45025": 144,
              "45027": 144,
              "45029": 144,
              "45031": 144,
              "45033": 144,
              "45035": 144,
              "45037": 144,
              "45039": 144,
              "45041": 144,
              "45043": 144,
              "45045": 144,
              "45047": 144,
              "45049": 144,
              "45051": 144,
              "45053": 144,
              "45055": 144,
              "45057": 144,
              "45059": 144,
              "45061": 144,
              "45063": 144,
              "45065": 144,
              "45067": 144,
              "45069": 144,
              "45071": 144,
              "45073": 144,
              "45075": 144,
              "45077": 144,
              "45079": 144,
              "45081": 144,
              "45083": 144,
              "45085": 144,
              "45087": 144,
              "45089": 144,
              "45091": 144,
              "46000": 144,
              "46003": 144,
              "46005": 144,
              "46007": 144,
              "46009": 144,
              "46011": 144,
              "46013": 144,
              "46015": 144,
              "46017": 144,
              "46019": 144,
              "46021": 144,
              "46023": 144,
              "46025": 144,
              "46027": 144,
              "46029": 144,
              "46031": 144,
              "46033": 144,
              "46035": 144,
              "46037": 144,
              "46039": 144,
              "46041": 144,
              "46043": 144,
              "46045": 144,
              "46047": 144,
              "46049": 144,
              "46051": 144,
              "46053": 144,
              "46055": 144,
              "46057": 144,
              "46059": 144,
              "46061": 144,
              "46063": 144,
              "46065": 144,
              "46067": 144,
              "46069": 144,
              "46071": 144,
              "46073": 144,
              "46075": 144,
              "46077": 144,
              "46079": 144,
              "46081": 144,
              "46083": 144,
              "46085": 144,
              "46087": 144,
              "46089": 144,
              "46091": 144,
              "46093": 144,
              "46095": 144,
              "46097": 144,
              "46099": 144,
              "46101": 144,
              "46103": 144,
              "46105": 144,
              "46107": 144,
              "46109": 144,
              "46111": 144,
              "46113": 144,
              "46115": 144,
              "46117": 144,
              "46119": 144,
              "46121": 144,
              "46123": 144,
              "46125": 144,
              "46127": 144,
              "46129": 144,
              "46135": 144,
              "46137": 144,
              "47000": 144,
              "47001": 144,
              "47003": 144,
              "47005": 144,
              "47007": 144,
              "47009": 144,
              "47011": 144,
              "47013": 144,
              "47015": 144,
              "47017": 144,
              "47019": 144,
              "47021": 144,
              "47023": 144,
              "47025": 144,
              "47027": 144,
              "47029": 144,
              "47031": 144,
              "47033": 144,
              "47035": 144,
              "47037": 144,
              "47039": 144,
              "47041": 144,
              "47043": 144,
              "47045": 144,
              "47047": 144,
              "47049": 144,
              "47051": 144,
              "47053": 144,
              "47055": 144,
              "47057": 144,
              "47059": 144,
              "47061": 144,
              "47063": 144,
              "47065": 144,
              "47067": 144,
              "47069": 144,
              "47071": 144,
              "47073": 144,
              "47075": 144,
              "47077": 144,
              "47079": 144,
              "47081": 144,
              "47083": 144,
              "47085": 144,
              "47087": 144,
              "47089": 144,
              "47091": 144,
              "47093": 144,
              "47095": 144,
              "47097": 144,
              "47099": 144,
              "47101": 144,
              "47103": 144,
              "47105": 144,
              "47107": 144,
              "47109": 144,
              "47111": 144,
              "47113": 144,
              "47115": 144,
              "47117": 144,
              "47119": 144,
              "47121": 144,
              "47123": 144,
              "47125": 144,
              "47127": 144,
              "47129": 144,
              "47131": 144,
              "47133": 144,
              "47135": 144,
              "47137": 144,
              "47139": 144,
              "47141": 144,
              "47143": 144,
              "47145": 144,
              "47147": 144,
              "47149": 144,
              "47151": 144,
              "47153": 144,
              "47155": 144,
              "47157": 144,
              "47159": 144,
              "47161": 144,
              "47163": 144,
              "47165": 144,
              "47167": 144,
              "47169": 144,
              "47171": 144,
              "47173": 144,
              "47175": 144,
              "47177": 144,
              "47179": 144,
              "47181": 144,
              "47183": 144,
              "47185": 144,
              "47187": 144,
              "47189": 144,
              "48000": 144,
              "48001": 144,
              "48003": 144,
              "48005": 144,
              "48007": 144,
              "48009": 144,
              "48011": 144,
              "48013": 144,
              "48015": 144,
              "48017": 144,
              "48019": 144,
              "48021": 144,
              "48023": 144,
              "48025": 144,
              "48027": 144,
              "48029": 144,
              "48031": 144,
              "48033": 144,
              "48035": 144,
              "48037": 144,
              "48039": 144,
              "48041": 144,
              "48043": 144,
              "48045": 144,
              "48047": 144,
              "48049": 144,
              "48051": 144,
              "48053": 144,
              "48055": 144,
              "48057": 144,
              "48059": 144,
              "48061": 144,
              "48063": 144,
              "48065": 144,
              "48067": 144,
              "48069": 144,
              "48071": 144,
              "48073": 144,
              "48075": 144,
              "48077": 144,
              "48079": 144,
              "48081": 144,
              "48083": 144,
              "48085": 144,
              "48087": 144,
              "48089": 144,
              "48091": 144,
              "48093": 144,
              "48095": 144,
              "48097": 144,
              "48099": 144,
              "48101": 144,
              "48103": 144,
              "48105": 144,
              "48107": 144,
              "48109": 144,
              "48111": 144,
              "48113": 144,
              "48115": 144,
              "48117": 144,
              "48119": 144,
              "48121": 144,
              "48123": 144,
              "48125": 144,
              "48127": 144,
              "48129": 144,
              "48131": 144,
              "48133": 144,
              "48135": 144,
              "48137": 144,
              "48139": 144,
              "48141": 144,
              "48143": 144,
              "48145": 144,
              "48147": 144,
              "48149": 144,
              "48151": 144,
              "48153": 144,
              "48155": 144,
              "48157": 144,
              "48159": 144,
              "48161": 144,
              "48163": 144,
              "48165": 144,
              "48167": 144,
              "48169": 144,
              "48171": 144,
              "48173": 144,
              "48175": 144,
              "48177": 144,
              "48179": 144,
              "48181": 144,
              "48183": 144,
              "48185": 144,
              "48187": 144,
              "48189": 144,
              "48191": 144,
              "48193": 144,
              "48195": 144,
              "48197": 144,
              "48199": 144,
              "48201": 144,
              "48203": 144,
              "48205": 144,
              "48207": 144,
              "48209": 144,
              "48211": 144,
              "48213": 144,
              "48215": 144,
              "48217": 144,
              "48219": 144,
              "48221": 144,
              "48223": 144,
              "48225": 144,
              "48227": 144,
              "48229": 144,
              "48231": 144,
              "48233": 144,
              "48235": 144,
              "48237": 144,
              "48239": 144,
              "48241": 144,
              "48243": 144,
              "48245": 144,
              "48247": 144,
              "48249": 144,
              "48251": 144,
              "48253": 144,
              "48255": 144,
              "48257": 144,
              "48259": 144,
              "48261": 144,
              "48263": 144,
              "48265": 144,
              "48267": 144,
              "48269": 144,
              "48271": 144,
              "48273": 144,
              "48275": 144,
              "48277": 144,
              "48279": 144,
              "48281": 144,
              "48283": 144,
              "48285": 144,
              "48287": 144,
              "48289": 144,
              "48291": 144,
              "48293": 144,
              "48295": 144,
              "48297": 144,
              "48299": 144,
              "48301": 144,
              "48303": 144,
              "48305": 144,
              "48307": 144,
              "48309": 144,
              "48311": 144,
              "48313": 144,
              "48315": 144,
              "48317": 144,
              "48319": 144,
              "48321": 144,
              "48323": 144,
              "48325": 144,
              "48327": 144,
              "48329": 144,
              "48331": 144,
              "48333": 144,
              "48335": 144,
              "48337": 144,
              "48339": 144,
              "48341": 144,
              "48343": 144,
              "48345": 144,
              "48347": 144,
              "48349": 144,
              "48351": 144,
              "48353": 144,
              "48355": 144,
              "48357": 144,
              "48359": 144,
              "48361": 144,
              "48363": 144,
              "48365": 144,
              "48367": 144,
              "48369": 144,
              "48371": 144,
              "48373": 144,
              "48375": 144,
              "48377": 144,
              "48379": 144,
              "48381": 144,
              "48383": 144,
              "48385": 144,
              "48387": 144,
              "48389": 144,
              "48391": 144,
              "48393": 144,
              "48395": 144,
              "48397": 144,
              "48399": 144,
              "48401": 144,
              "48403": 144,
              "48405": 144,
              "48407": 144,
              "48409": 144,
              "48411": 144,
              "48413": 144,
              "48415": 144,
              "48417": 144,
              "48419": 144,
              "48421": 144,
              "48423": 144,
              "48425": 144,
              "48427": 144,
              "48429": 144,
              "48431": 144,
              "48433": 144,
              "48435": 144,
              "48437": 144,
              "48439": 144,
              "48441": 144,
              "48443": 144,
              "48445": 144,
              "48447": 144,
              "48449": 144,
              "48451": 144,
              "48453": 144,
              "48455": 144,
              "48457": 144,
              "48459": 144,
              "48461": 144,
              "48463": 144,
              "48465": 144,
              "48467": 144,
              "48469": 144,
              "48471": 144,
              "48473": 144,
              "48475": 144,
              "48477": 144,
              "48479": 144,
              "48481": 144,
              "48483": 144,
              "48485": 144,
              "48487": 144,
              "48489": 144,
              "48491": 144,
              "48493": 144,
              "48495": 144,
              "48497": 144,
              "48499": 144,
              "48501": 144,
              "48503": 144,
              "48505": 144,
              "48507": 144,
              "49000": 144,
              "49001": 144,
              "49003": 144,
              "49005": 144,
              "49007": 144,
              "49009": 144,
              "49011": 144,
              "49013": 144,
              "49015": 144,
              "49017": 144,
              "49019": 144,
              "49021": 144,
              "49023": 144,
              "49025": 144,
              "49027": 144,
              "49029": 144,
              "49031": 144,
              "49033": 144,
              "49035": 144,
              "49037": 144,
              "49039": 144,
              "49041": 144,
              "49043": 144,
              "49045": 144,
              "49047": 144,
              "49049": 144,
              "49051": 144,
              "49053": 144,
              "49055": 144,
              "49057": 144,
              "5000": 144,
              "50000": 144,
              "50001": 144,
              "50003": 144,
              "50005": 144,
              "50007": 144,
              "50009": 144,
              "5001": 144,
              "50011": 144,
              "50013": 144,
              "50015": 144,
              "50017": 144,
              "50019": 144,
              "50021": 144,
              "50023": 144,
              "50025": 144,
              "50027": 144,
              "5003": 144,
              "5005": 144,
              "5007": 144,
              "5009": 144,
              "5011": 144,
              "5013": 144,
              "5015": 144,
              "5017": 144,
              "5019": 144,
              "5021": 144,
              "5023": 144,
              "5025": 144,
              "5027": 144,
              "5029": 144,
              "5031": 144,
              "5033": 144,
              "5035": 144,
              "5037": 144,
              "5039": 144,
              "5041": 144,
              "5043": 144,
              "5045": 144,
              "5047": 144,
              "5049": 144,
              "5051": 144,
              "5053": 144,
              "5055": 144,
              "5057": 144,
              "5059": 144,
              "5061": 144,
              "5063": 144,
              "5065": 144,
              "5067": 144,
              "5069": 144,
              "5071": 144,
              "5073": 144,
              "5075": 144,
              "5077": 144,
              "5079": 144,
              "5081": 144,
              "5083": 144,
              "5085": 144,
              "5087": 144,
              "5089": 144,
              "5091": 144,
              "5093": 144,
              "5095": 144,
              "5097": 144,
              "5099": 144,
              "51000": 144,
              "51001": 144,
              "51003": 144,
              "51005": 144,
              "51007": 144,
              "51009": 144,
              "5101": 144,
              "51011": 144,
              "51013": 144,
              "51015": 144,
              "51017": 144,
              "51019": 144,
              "51021": 144,
              "51023": 144,
              "51025": 144,
              "51027": 144,
              "51029": 144,
              "5103": 144,
              "51031": 144,
              "51033": 144,
              "51035": 144,
              "51036": 144,
              "51037": 144,
              "51041": 144,
              "51043": 144,
              "51045": 144,
              "51047": 144,
              "51049": 144,
              "5105": 144,
              "51051": 144,
              "51053": 144,
              "51057": 144,
              "51059": 144,
              "51061": 144,
              "51063": 144,
              "51065": 144,
              "51067": 144,
              "51069": 144,
              "5107": 144,
              "51071": 144,
              "51073": 144,
              "51075": 144,
              "51077": 144,
              "51079": 144,
              "51081": 144,
              "51083": 144,
              "51085": 144,
              "51087": 144,
              "51089": 144,
              "5109": 144,
              "51091": 144,
              "51093": 144,
              "51095": 144,
              "51097": 144,
              "51099": 144,
              "51101": 144,
              "51103": 144,
              "51105": 144,
              "51107": 144,
              "51109": 144,
              "5111": 144,
              "51111": 144,
              "51113": 144,
              "51115": 144,
              "51117": 144,
              "51119": 144,
              "51121": 144,
              "51125": 144,
              "51127": 144,
              "5113": 144,
              "51131": 144,
              "51133": 144,
              "51135": 144,
              "51137": 144,
              "51139": 144,
              "51141": 144,
              "51143": 144,
              "51145": 144,
              "51147": 144,
              "51149": 144,
              "5115": 144,
              "51153": 144,
              "51155": 144,
              "51157": 144,
              "51159": 144,
              "51161": 144,
              "51163": 144,
              "51165": 144,
              "51167": 144,
              "51169": 144,
              "5117": 144,
              "51171": 144,
              "51173": 144,
              "51175": 144,
              "51177": 144,
              "51179": 144,
              "51181": 144,
              "51183": 144,
              "51185": 144,
              "51187": 144,
              "5119": 144,
              "51191": 144,
              "51193": 144,
              "51195": 144,
              "51197": 144,
              "51199": 144,
              "5121": 144,
              "5123": 144,
              "5125": 144,
              "5127": 144,
              "5129": 144,
              "5131": 144,
              "5133": 144,
              "5135": 144,
              "5137": 144,
              "5139": 144,
              "5141": 144,
              "5143": 144,
              "5145": 144,
              "5147": 144,
              "5149": 144,
              "51510": 144,
              "51515": 144,
              "51520": 144,
              "51530": 144,
              "51540": 144,
              "51550": 144,
              "51570": 144,
              "51580": 144,
              "51590": 144,
              "51595": 144,
              "51600": 144,
              "51610": 144,
              "51620": 144,
              "51630": 144,
              "51640": 144,
              "51650": 144,
              "51660": 144,
              "51670": 144,
              "51678": 144,
              "51680": 144,
              "51683": 144,
              "51685": 144,
              "51690": 144,
              "51700": 144,
              "51710": 144,
              "51720": 144,
              "51730": 144,
              "51735": 144,
              "51740": 144,
              "51750": 144,
              "51760": 144,
              "51770": 144,
              "51775": 144,
              "51790": 144,
              "51800": 144,
              "51810": 144,
              "51820": 144,
              "51830": 144,
              "51840": 144,
              "53000": 144,
              "53001": 144,
              "53003": 144,
              "53005": 144,
              "53007": 144,
              "53009": 144,
              "53011": 144,
              "53013": 144,
              "53015": 144,
              "53017": 144,
              "53019": 144,
              "53021": 144,
              "53023": 144,
              "53025": 144,
              "53027": 144,
              "53029": 144,
              "53031": 144,
              "53033": 144,
              "53035": 144,
              "53037": 144,
              "53039": 144,
              "53041": 144,
              "53043": 144,
              "53045": 144,
              "53047": 144,
              "53049": 144,
              "53051": 144,
              "53053": 144,
              "53055": 144,
              "53057": 144,
              "53059": 144,
              "53061": 144,
              "53063": 144,
              "53065": 144,
              "53067": 144,
              "53069": 144,
              "53071": 144,
              "53073": 144,
              "53075": 144,
              "53077": 144,
              "54000": 144,
              "54001": 144,
              "54003": 144,
              "54005": 144,
              "54007": 144,
              "54009": 144,
              "54011": 144,
              "54013": 144,
              "54015": 144,
              "54017": 144,
              "54019": 144,
              "54021": 144,
              "54023": 144,
              "54025": 144,
              "54027": 144,
              "54029": 144,
              "54031": 144,
              "54033": 144,
              "54035": 144,
              "54037": 144,
              "54039": 144,
              "54041": 144,
              "54043": 144,
              "54045": 144,
              "54047": 144,
              "54049": 144,
              "54051": 144,
              "54053": 144,
              "54055": 144,
              "54057": 144,
              "54059": 144,
              "54061": 144,
              "54063": 144,
              "54065": 144,
              "54067": 144,
              "54069": 144,
              "54071": 144,
              "54073": 144,
              "54075": 144,
              "54077": 144,
              "54079": 144,
              "54081": 144,
              "54083": 144,
              "54085": 144,
              "54087": 144,
              "54089": 144,
              "54091": 144,
              "54093": 144,
              "54095": 144,
              "54097": 144,
              "54099": 144,
              "54101": 144,
              "54103": 144,
              "54105": 144,
              "54107": 144,
              "54109": 144,
              "55000": 144,
              "55001": 144,
              "55003": 144,
              "55005": 144,
              "55007": 144,
              "55009": 144,
              "55011": 144,
              "55013": 144,
              "55015": 144,
              "55017": 144,
              "55019": 144,
              "55021": 144,
              "55023": 144,
              "55025": 144,
              "55027": 144,
              "55029": 144,
              "55031": 144,
              "55033": 144,
              "55035": 144,
              "55037": 144,
              "55039": 144,
              "55041": 144,
              "55043": 144,
              "55045": 144,
              "55047": 144,
              "55049": 144,
              "55051": 144,
              "55053": 144,
              "55055": 144,
              "55057": 144,
              "55059": 144,
              "55061": 144,
              "55063": 144,
              "55065": 144,
              "55067": 144,
              "55069": 144,
              "55071": 144,
              "55073": 144,
              "55075": 144,
              "55077": 144,
              "55078": 144,
              "55079": 144,
              "55081": 144,
              "55083": 144,
              "55085": 144,
              "55087": 144,
              "55089": 144,
              "55091": 144,
              "55093": 144,
              "55095": 144,
              "55097": 144,
              "55099": 144,
              "55101": 144,
              "55103": 144,
              "55105": 144,
              "55107": 144,
              "55109": 144,
              "55111": 144,
              "55113": 144,
              "55115": 144,
              "55117": 144,
              "55119": 144,
              "55121": 144,
              "55123": 144,
              "55125": 144,
              "55127": 144,
              "55129": 144,
              "55131": 144,
              "55133": 144,
              "55135": 144,
              "55137": 144,
              "55139": 144,
              "55141": 144,
              "56000": 144,
              "56001": 144,
              "56003": 144,
              "56005": 144,
              "56007": 144,
              "56009": 144,
              "56011": 144,
              "56013": 144,
              "56015": 144,
              "56017": 144,
              "56019": 144,
              "56021": 144,
              "56023": 144,
              "56025": 144,
              "56027": 144,
              "56029": 144,
              "56031": 144,
              "56033": 144,
              "56035": 144,
              "56037": 144,
              "56039": 144,
              "56041": 144,
              "56043": 144,
              "56045": 144,
              "6000": 144,
              "6001": 144,
              "6003": 144,
              "6005": 144,
              "6007": 144,
              "6009": 144,
              "6011": 144,
              "6013": 144,
              "6015": 144,
              "6017": 144,
              "6019": 144,
              "6021": 144,
              "6023": 144,
              "6025": 144,
              "6027": 144,
              "6029": 144,
              "6031": 144,
              "6033": 144,
              "6035": 144,
              "6037": 144,
              "6039": 144,
              "6041": 144,
              "6043": 144,
              "6045": 144,
              "6047": 144,
              "6049": 144,
              "6051": 144,
              "6053": 144,
              "6055": 144,
              "6057": 144,
              "6059": 144,
              "6061": 144,
              "6063": 144,
              "6065": 144,
              "6067": 144,
              "6069": 144,
              "6071": 144,
              "6073": 144,
              "6075": 144,
              "6077": 144,
              "6079": 144,
              "6081": 144,
              "6083": 144,
              "6085": 144,
              "6087": 144,
              "6089": 144,
              "6091": 144,
              "6093": 144,
              "6095": 144,
              "6097": 144,
              "6099": 144,
              "6101": 144,
              "6103": 144,
              "6105": 144,
              "6107": 144,
              "6109": 144,
              "6111": 144,
              "6113": 144,
              "6115": 144,
              "8000": 144,
              "8001": 144,
              "8003": 144,
              "8005": 144,
              "8007": 144,
              "8009": 144,
              "8011": 144,
              "8013": 144,
              "8014": 144,
              "8015": 144,
              "8017": 144,
              "8019": 144,
              "8021": 144,
              "8023": 144,
              "8025": 144,
              "8027": 144,
              "8029": 144,
              "8031": 144,
              "8033": 144,
              "8035": 144,
              "8037": 144,
              "8039": 144,
              "8041": 144,
              "8043": 144,
              "8045": 144,
              "8047": 144,
              "8049": 144,
              "8051": 144,
              "8053": 144,
              "8055": 144,
              "8057": 144,
              "8059": 144,
              "8061": 144,
              "8063": 144,
              "8065": 144,
              "8067": 144,
              "8069": 144,
              "8071": 144,
              "8073": 144,
              "8075": 144,
              "8077": 144,
              "8079": 144,
              "8081": 144,
              "8083": 144,
              "8085": 144,
              "8087": 144,
              "8089": 144,
              "8091": 144,
              "8093": 144,
              "8095": 144,
              "8097": 144,
              "8099": 144,
              "8101": 144,
              "8103": 144,
              "8105": 144,
              "8107": 144,
              "8109": 144,
              "8111": 144,
              "8113": 144,
              "8115": 144,
              "8117": 144,
              "8119": 144,
              "8121": 144,
              "8123": 144,
              "8125": 144,
              "9000": 144,
              "9001": 144,
              "9003": 144,
              "9005": 144,
              "9007": 144,
              "9009": 144,
              "9011": 144,
              "9013": 144,
              "9015": 144
            }
          },
          {
            "name": "time",
            "duplicates": 442944,
            "time_range": [0, 143],
            "type": "string",
            "missing": 0,
            "table": {
              "2022-10-01": 3077,
              "2022-10-08": 3077,
              "2022-10-15": 3077,
              "2022-10-22": 3077,
              "2022-10-29": 3077,
              "2022-11-05": 3077,
              "2022-11-12": 3077,
              "2022-11-19": 3077,
              "2022-11-26": 3077,
              "2022-12-03": 3077,
              "2022-12-10": 3077,
              "2022-12-17": 3077,
              "2022-12-24": 3077,
              "2022-12-31": 3077,
              "2023-01-07": 3077,
              "2023-01-14": 3077,
              "2023-01-21": 3077,
              "2023-01-28": 3077,
              "2023-02-04": 3077,
              "2023-02-11": 3077,
              "2023-02-18": 3077,
              "2023-02-25": 3077,
              "2023-03-04": 3077,
              "2023-03-11": 3077,
              "2023-03-18": 3077,
              "2023-03-25": 3077,
              "2023-04-01": 3077,
              "2023-04-08": 3077,
              "2023-04-15": 3077,
              "2023-04-22": 3077,
              "2023-04-29": 3077,
              "2023-05-06": 3077,
              "2023-05-13": 3077,
              "2023-05-20": 3077,
              "2023-05-27": 3077,
              "2023-06-03": 3077,
              "2023-06-10": 3077,
              "2023-06-17": 3077,
              "2023-06-24": 3077,
              "2023-07-01": 3077,
              "2023-07-08": 3077,
              "2023-07-15": 3077,
              "2023-07-22": 3077,
              "2023-07-29": 3077,
              "2023-08-05": 3077,
              "2023-08-12": 3077,
              "2023-08-19": 3077,
              "2023-08-26": 3077,
              "2023-09-02": 3077,
              "2023-09-09": 3077,
              "2023-09-16": 3077,
              "2023-09-23": 3077,
              "2023-09-30": 3077,
              "2023-10-07": 3077,
              "2023-10-14": 3077,
              "2023-10-21": 3077,
              "2023-10-28": 3077,
              "2023-11-04": 3077,
              "2023-11-11": 3077,
              "2023-11-18": 3077,
              "2023-11-25": 3077,
              "2023-12-02": 3077,
              "2023-12-09": 3077,
              "2023-12-16": 3077,
              "2023-12-23": 3077,
              "2023-12-30": 3077,
              "2024-01-06": 3077,
              "2024-01-13": 3077,
              "2024-01-20": 3077,
              "2024-01-27": 3077,
              "2024-02-03": 3077,
              "2024-02-10": 3077,
              "2024-02-17": 3077,
              "2024-02-24": 3077,
              "2024-03-02": 3077,
              "2024-03-09": 3077,
              "2024-03-16": 3077,
              "2024-03-23": 3077,
              "2024-03-30": 3077,
              "2024-04-06": 3077,
              "2024-04-13": 3077,
              "2024-04-20": 3077,
              "2024-04-27": 3077,
              "2024-05-04": 3077,
              "2024-05-11": 3077,
              "2024-05-18": 3077,
              "2024-05-25": 3077,
              "2024-06-01": 3077,
              "2024-06-08": 3077,
              "2024-06-15": 3077,
              "2024-06-22": 3077,
              "2024-06-29": 3077,
              "2024-07-06": 3077,
              "2024-07-13": 3077,
              "2024-07-20": 3077,
              "2024-07-27": 3077,
              "2024-08-03": 3077,
              "2024-08-10": 3077,
              "2024-08-17": 3077,
              "2024-08-24": 3077,
              "2024-08-31": 3077,
              "2024-09-07": 3077,
              "2024-09-14": 3077,
              "2024-09-21": 3077,
              "2024-09-28": 3077,
              "2024-10-05": 3077,
              "2024-10-12": 3077,
              "2024-10-19": 3077,
              "2024-10-26": 3077,
              "2024-11-02": 3077,
              "2024-11-09": 3077,
              "2024-11-16": 3077,
              "2024-11-23": 3077,
              "2024-11-30": 3077,
              "2024-12-07": 3077,
              "2024-12-14": 3077,
              "2024-12-21": 3077,
              "2024-12-28": 3077,
              "2025-01-04": 3077,
              "2025-01-11": 3077,
              "2025-01-18": 3077,
              "2025-01-25": 3077,
              "2025-02-01": 3077,
              "2025-02-08": 3077,
              "2025-02-15": 3077,
              "2025-02-22": 3077,
              "2025-03-01": 3077,
              "2025-03-08": 3077,
              "2025-03-15": 3077,
              "2025-03-22": 3077,
              "2025-03-29": 3077,
              "2025-04-05": 3077,
              "2025-04-12": 3077,
              "2025-04-19": 3077,
              "2025-04-26": 3077,
              "2025-05-03": 3077,
              "2025-05-10": 3077,
              "2025-05-17": 3077,
              "2025-05-24": 3077,
              "2025-05-31": 3077,
              "2025-06-07": 3077,
              "2025-06-14": 3077,
              "2025-06-21": 3077,
              "2025-06-28": 3077
            }
          },
          {
            "name": "percent_visits_rsv",
            "duplicates": 442445,
            "time_range": [0, 143],
            "type": "float",
            "missing": 113760,
            "mean": 0.349127,
            "sd": 0.722546,
            "min": 0,
            "max": 50
          },
          {
            "name": "percent_visits_flu",
            "duplicates": 441230,
            "time_range": [0, 143],
            "type": "float",
            "missing": 113760,
            "mean": 1.567886,
            "sd": 2.816411,
            "min": 0,
            "max": 100
          },
          {
            "name": "percent_visits_covid",
            "duplicates": 442108,
            "time_range": [0, 143],
            "type": "float",
            "missing": 113760,
            "mean": 1.428396,
            "sd": 1.385081,
            "min": 0,
            "max": 100
          }
        ]
      },
      "sha512": "66d89f209ca3413cbb01635577c42dc3a79e9d57123ad72feabad01f47effa6ffe6e231941b283a18adacb81cb7f1f5f3770251678fa46151cd6da25a5b3f91b"
    }
  ],
  "measure_info": {
    "percent_visits_rsv": {
      "full_name": "Percent of Emergency department visits coded as being caused by RSV",
      "measure": "percent",
      "short_name": "RSV Percent in the ED",
      "long_name": "Percent of ED visits caused by RSV",
      "category": "respiratory_diseases",
      "long_description": "The National Syndromic Surveillance Program (NSSP) provides data on emergency department visits for influenza, respiratory syncytial virus, and COVID-19 each week, organized by state and county, where available. The numbers are based on recorded diagnoses. NSSP data are made available by the CDC.",
      "time_resolution": "weekly",
      "sources": [],
      "citations": [],
      "layer": []
    },
    "percent_visits_flu": {
      "full_name": "Percent of Emergency department visits coded as being caused by influenza",
      "measure": "percent",
      "short_name": "Influenza Percent in the ED",
      "long_name": "Percent of ED visits caused by Influenza",
      "category": "respiratory_diseases",
      "long_description": "The National Syndromic Surveillance Program (NSSP) provides data on emergency department visits for influenza, respiratory syncytial virus, and COVID-19 each week, organized by state and county, where available. The numbers are based on recorded diagnoses. NSSP data are made available by the CDC.",
      "time_resolution": "weekly",
      "sources": [],
      "citations": [],
      "layer": []
    },
    "percent_visits_covid": {
      "full_name": "Percent of Emergency department visits coded as being caused by covid",
      "measure": "percent",
      "short_name": "COVID-19 Percent in the ED",
      "long_name": "Percent of ED visits caused by COVID-19",
      "category": "respiratory_diseases",
      "long_description": "The National Syndromic Surveillance Program (NSSP) provides data on emergency department visits for influenza, respiratory syncytial virus, and COVID-19 each week, organized by state and county, where available. The numbers are based on recorded diagnoses. NSSP data are made available by the CDC.",
      "time_resolution": "weekly",
      "sources": [],
      "citations": [],
      "layer": []
    }
  }
}
