{
  "pct_obesity_value": {
    "full_name": "Percent of the Population with BMI >30",
    "measure": "",
    "short_name": "",
    "long_name": "",
    "category": "",
    "short_description": "",
    "long_description": "",
    "statement": "",
    "measure_type": "Prevalence",
    "unit": "Percent",
    "time_resolution": "year",
    "sources": [],
    "citations": [],
    "layer": []
  },
    "pct_diabetes_value": {
    "full_name": "Percent of the Population that has been told by their provider that they have diabetes",
    "measure": "",
    "short_name": "",
    "long_name": "",
    "category": "",
    "short_description": "",
    "long_description": "",
    "statement": "",
    "measure_type": "Prevalence",
    "unit": "Percent",
    "time_resolution": "year",
    "sources": [],
    "citations": [],
    "layer": []
  },
      "age": {
    "full_name": "Age group",
    "measure": "",
    "short_name": "",
    "long_name": "",
    "category": "",
    "short_description": "",
    "long_description": "",
    "statement": "",
    "measure_type": "Age",
    "unit": "years",
    "time_resolution": "year",
    "sources": [],
    "citations": [],
    "layer": []
  },
      "pct_diabetes_sample_size": {
    "full_name": "Number of people who responded that they have been told by a healthcare provider they have diabetes",
    "measure": "",
    "short_name": "",
    "long_name": "",
    "category": "",
    "short_description": "",
    "long_description": "",
    "statement": "",
    "measure_type": "Number",
    "unit": "integer",
    "time_resolution": "year",
    "sources": [],
    "citations": [],
    "layer": []
  },
      "pct_obesity_sample_size": {
    "full_name": "Number of survey respondents with a calculated BMI >30",
    "measure": "",
    "short_name": "",
    "long_name": "",
    "category": "",
    "short_description": "",
    "long_description": "",
    "statement": "",
    "measure_type": "Number",
    "unit": "integer",
    "time_resolution": "year",
    "sources": [],
    "citations": [],
    "layer": []
  },
    "pct_diabetes_value_lcl": {
    "full_name": "Lower Bound of the 95% confidence interval for the percent of the Population that has been told by their provider that they have diabetes",
    "measure": "",
    "short_name": "",
    "long_name": "",
    "category": "",
    "short_description": "",
    "long_description": "",
    "statement": "",
    "measure_type": "Prevalence",
    "unit": "Percent",
    "time_resolution": "year",
    "sources": [],
    "citations": [],
    "layer": []
  },
    "pct_diabetes_value_ucl": {
    "full_name": "Upper Bound of the 95% confidence interval for the percent of the Population that has been told by their provider that they have diabetes",
    "measure": "",
    "short_name": "",
    "long_name": "",
    "category": "",
    "short_description": "",
    "long_description": "",
    "statement": "",
    "measure_type": "Prevalence",
    "unit": "Percent",
    "time_resolution": "year",
    "sources": [],
    "citations": [],
    "layer": []
  },
  "pct_obesity_value_lcl": {
    "full_name": "Lower Bound of the 95% confidence interval for the percent of the Population with BMI >30",
    "measure": "",
    "short_name": "",
    "long_name": "",
    "category": "",
    "short_description": "",
    "long_description": "",
    "statement": "",
    "measure_type": "Prevalence",
    "unit": "Percent",
    "time_resolution": "year",
    "sources": [],
    "citations": [],
    "layer": []
  },
  "pct_obesity_value_ucl": {
    "full_name": "Upper Bound of the 95% confidence interval for the percent of the Population with BMI >30",
    "measure": "",
    "short_name": "",
    "long_name": "",
    "category": "",
    "short_description": "",
    "long_description": "",
    "statement": "",
    "measure_type": "Prevalence",
    "unit": "Percent",
    "time_resolution": "year",
    "sources": [],
    "citations": [],
    "layer": []
  }
}
